password_maker/__init__.py
password_maker/generate.py
password_maker-0.0.3.dist-info/METADATA
password_maker-0.0.3.dist-info/WHEEL
password_maker-0.0.3.dist-info/top_level.txt
password_maker-0.0.3.dist-info/RECORD
