Metadata-Version: 2.1
Name: password-maker
Version: 0.0.3
Summary: A module that generates a random password
Home-page: https://github.com/RuhamLeal/making_package_module
Author: Ruham Leal
Author-email: ruhamxlpro@hotmail.com
Requires-Python: >=3.8
